{
    "pollo" : ["239 kcal", "100 gr"],
    "huevo" : ["155 kcal", "100 gr"],
    "carne de vaca" : ["250 kcal", "120 gr"],
    "ensalada" : ["70 kcal", "150 gr"],
    "arroz" : ["110 kcal", "100 gr"],
    "lentejas" : ["230 kcal", "180 gr"],
    "salmon" : ["180 kcal", "120 gr"],
    "zanahoria" : ["45 kcal", "80 gr"],
    "plátano" : ["105 kcal", "100 gr"],
    "queso" : ["160 kcal", "50 gr"],
    "frijoles" : ["225 kcal", "150 gr"],
    "champiñones" : ["50 kcal", "80 gr"],
    "espinacas" : ["20 kcal", "20 gr"],
    "garbanzos" : ["160 kcal", "100 gr"],
    "pavo" : ["140 kcal", "100 gr"],
    "lechuga" : ["10 kcal", "20 gr"],
    "pan" : ["120 kcal", "50 gr"],
    "tomate" : ["22 kcal", "60 gr"],
    "pepino" : ["15 kcal", "40 gr"],
    "calabacín" : ["25 kcal", "60 gr"],
    "berenjena" : ["25 kcal", "60 gr"],
    "aguacate" : ["160 kcal", "100 gr"],
    "naranja" : ["47 kcal", "100 gr"],
    "manzana" : ["52 kcal", "100 gr"],
    "pera" : ["57 kcal", "100 gr"],
    "mango" : ["51 kcal", "100 gr"],
    "piña" : ["51 kcal", "100 gr"],
    "fresa" : ["32 kcal", "100 gr"],
    "frambuesa" : ["32 kcal", "100 gr"],
    "arándano" : ["46 kcal", "100 gr"],
    "ciruela" : ["46 kcal", "100 gr"],
    "higos" : ["48 kcal", "100 gr"],
    "dátiles" : ["277 kcal", "100 gr"],
    "almendras" : ["575 kcal", "100 gr"],
    "cacahuates" : ["575 kcal", "100 gr"],
    "nueces" : ["654 kcal", "100 gr"],
    "avellanas" : ["654 kcal", "100 gr"],
    "castañas" : ["161 kcal", "100 gr"],
    "chocolate" : ["535 kcal", "100 gr"],
    "yogur" : ["59 kcal", "100 gr"],
    "leche" : ["50 kcal", "100 gr"],
    "queso feta" : ["264 kcal", "100 gr"],
    "queso parmesano" : ["264 kcal", "100 gr"],
    "queso mozzarella" : ["264 kcal", "100 gr"],
    "atún" : ["144 kcal", "100 gr"],
    "salmón ahumado" : ["144 kcal", "100 gr"],
    "camarón" : ["120 kcal", "100 gr"],
    "langostinos" : ["120 kcal", "100 gr"],
    "mejillones" : ["120 kcal", "100 gr"],
    "champiñones portobello" : ["50 kcal", "80 gr"],
    "champiñones cremini" : ["50 kcal", "80 gr"],
    "champiñones shiitake" : ["50 kcal", "80 gr"],
    "espinacas baby" : ["20 kcal", "20 gr"],
    "espinacas congeladas" : ["20 kcal", "20 gr"],
    "garbanzos cocidos" : ["160 kcal", "100 gr"],
    "garbanzos enlatados" : ["160 kcal", "100 gr"],
    "pavo asado" : ["140 kcal", "100 gr"],
    "pavo cocido" : ["140 kcal", "100 gr"],
    "lechuga romana" : ["10 kcal", "20 gr"],
    "lechuga iceberg" : ["10 kcal", "20 gr"],
    "lechuga butter" : ["10 kcal", "20 gr"],
    "zanahoria baby" : ["45 kcal", "80 gr"],
    "zanahoria congelada" : ["45 kcal", "80 gr"],
    "brocoli" : ["55 kcal", "100 gr"],
    "brócoli al vapor" : ["55 kcal", "100 gr"],
    "col rizada" : ["45 kcal", "100 gr"],
    "col rizada al vapor" : ["45 kcal", "100 gr"],
    "zanahoria asada" : ["45 kcal", "80 gr"],
    "zanahoria al vapor" : ["45 kcal", "80 gr"],
    "calabacín asado" : ["25 kcal", "60 gr"],
    "calabacín al vapor" : ["25 kcal", "60 gr"],
    "berenjena asada" : ["25 kcal", "60 gr"],
    "berenjena al vapor" : ["25 kcal", "60 gr"],
    "pimiento rojo" : ["45 kcal", "100 gr"],
    "pimiento verde" : ["45 kcal", "100 gr"],
    "cebolla" : ["45 kcal", "100 gr"],
    "ajo" : ["45 kcal", "100 gr"],
    "perejil" : ["20 kcal", "20 gr"],
    "orégano" : ["20 kcal", "20 gr"],
    "albahaca" : ["20 kcal", "20 gr"],
    "tomate cherry" : ["22 kcal", "60 gr"],
    "tomate grande" : ["22 kcal", "100 gr"],
    "sandía" : ["30 kcal", "100 gr"],
    "melón" : ["30 kcal", "100 gr"],
    "higos secos" : ["48 kcal", "100 gr"],
    "dátiles secos" : ["277 kcal", "100 gr"],
    "almendras tostadas" : ["575 kcal", "100 gr"],
    "cacahuates tostados" : ["575 kcal", "100 gr"],
    "nueces tostadas" : ["654 kcal", "100 gr"],
    "avellanas tostadas" : ["654 kcal", "100 gr"],
    "castañas tostadas" : ["161 kcal", "100 gr"],
    "chocolate negro" : ["535 kcal", "100 gr"],
    "chocolate con leche" : ["535 kcal", "100 gr"],
    "yogur natural" : ["59 kcal", "100 gr"],
    "yogur con frutas" : ["59 kcal", "100 gr"],
    "leche descremada" : ["50 kcal", "100 gr"],
    "leche entera" : ["50 kcal", "100 gr"],
    "queso feta light" : ["264 kcal", "100 gr"],
    "queso parmesano light" : ["264 kcal", "100 gr"],
    "queso mozzarella light" : ["264 kcal", "100 gr"],
    "atún enlatado" : ["144 kcal", "100 gr"],
    "salmón ahumado enlatado" : ["144 kcal", "100 gr"],
    "camarón congelado" : ["120 kcal", "100 gr"],
    "langostinos congelados" : ["120 kcal", "100 gr"],
    "mejillones congelados" : ["120 kcal", "100 gr"],
    "champiñones portobello congelados" : ["50 kcal", "80 gr"],
    "champiñones cremini congelados" : ["50 kcal", "80 gr"],
    "champiñones shiitake congelados" : ["50 kcal", "80 gr"],
    "espinacas baby congeladas" : ["20 kcal", "20 gr"],
    "espinacas_congeladas" : ["20 kcal", "20 gr"],
    "garbanzos cocidos enlatados" : ["160 kcal", "100 gr"],
    "garbanzos_enlatados" : ["160 kcal", "100 gr"],
    "pavo asado congelado" : ["140 kcal", "100 gr"],
    "pavo cocido congelado" : ["140 kcal", "100 gr"],
    "lechuga romana congelada" : ["10 kcal", "20 gr"],
    "lechuga iceberg congelada" : ["10 kcal", "20 gr"],
    "lechuga butter congelada" : ["10 kcal", "20 gr"]
  }
